easy_route/__init__.py
easy_route/controllers/__init__.py
easy_route/controllers/abstract_controller.py
easy_route/middlewares/__init__.py
easy_route/middlewares/abstract_middleware.py
easy_route/middlewares/data_validator_middleware.py
easy_route/routes/__init__.py
easy_route/routes/route.py
easy_route-0.0.2.dist-info/METADATA
easy_route-0.0.2.dist-info/WHEEL
easy_route-0.0.2.dist-info/licenses/LICENSE
easy_route-0.0.2.dist-info/RECORD
