Metadata-Version: 2.1
Name: easy_route
Version: 0.0.2
Summary: A simple Flask routing package.
Project-URL: Homepage, https://github.com/en0mia/easy-route
Project-URL: Bug Tracker, https://github.com/en0mia/easy-route/issues
Author-email: Simone Nicol <en0mia.dev@gmail.com>
License-File: LICENSE
Classifier: License :: OSI Approved :: MIT License
Classifier: Operating System :: OS Independent
Classifier: Programming Language :: Python :: 3
Requires-Python: >=3.11
